FinNews/__init__.py
FinNews/feed.py
FinNews/rss.db
FinNews/source_object.py
FinNews/sources.py
FinNews-1.1.0.dist-info/LICENSE
FinNews-1.1.0.dist-info/METADATA
FinNews-1.1.0.dist-info/WHEEL
FinNews-1.1.0.dist-info/top_level.txt
FinNews-1.1.0.dist-info/RECORD
