Metadata-Version: 2.1
Name: FinNews
Version: 1.1.0
Summary: Package for gathering financial news from various RSS feeds
Home-page: https://github.com/scaratozzolo/FinNews
Author: Scott Caratozzolo
Author-email: scaratozzolo12@gmail.com
License: UNKNOWN
Platform: UNKNOWN
Classifier: Programming Language :: Python :: 3.7
Classifier: License :: OSI Approved :: MIT License
Classifier: Operating System :: OS Independent
